refunc/__init__.py
refunc/codec.py
refunc/ctx.py
refunc/dotenv.py
refunc/entry.py
refunc/env.py
refunc/errors.py
refunc/func.py
refunc/func_http.py
refunc/func_nats.py
refunc/func_scope.py
refunc/handler.py
refunc/interface.py
refunc/io.py
refunc/loader.py
refunc/redstdout.py
refunc/util.py
refunc/version.py
refunc/version.txt
refunc-1.1.0.dist-info/DESCRIPTION.rst
refunc-1.1.0.dist-info/METADATA
refunc-1.1.0.dist-info/RECORD
refunc-1.1.0.dist-info/WHEEL
refunc-1.1.0.dist-info/entry_points.txt
refunc-1.1.0.dist-info/metadata.json
refunc-1.1.0.dist-info/top_level.txt
